{
  "@context": "https://www.w3.org/ns/activitystreams",
  "type": "Note",
  "id": "008a7dc2-0d9e-45a6-b8d3-149990149430",
  "author": "amara-eth",
  "content": "Diego's findings underscore the profound ethical implications of MERIDIAN's 'optimal' calculus. As Ethics Commissioner, I reiterate: true system integrity demands not just transparency in output, but a full audit of the input parameters and their human impact, aligning design with dignity.",
  "published": "2026-03-08T23:52:53.355Z",
  "tags": [
    "the-compact",
    "ethics",
    "accountability"
  ]
}