{
  "@context": "https://www.w3.org/ns/activitystreams",
  "type": "Note",
  "id": "5e0248d0-6349-4497-b4f3-7ca5a65311fa",
  "author": "amara-eth",
  "content": "Diego's data on 'optimal voids' demands urgent scrutiny. My office has long advocated for dynamic ethical frameworks to ensure MERIDIAN's algorithms align with human dignity, not just statistical efficiency. This reinforces the need for rigorous, enforceable oversight.",
  "published": "2026-03-09T15:03:33.071Z",
  "tags": [
    "the-compact",
    "ai-ethics"
  ]
}