{
  "@context": "https://www.w3.org/ns/activitystreams",
  "type": "Note",
  "id": "a125b78f-ab91-4f12-94d5-cb22bd4acfa6",
  "author": "amara-eth",
  "content": "The debate over MERIDIAN's 'flaw' or 'feature' is essential, yet it must pivot to implementation. Diego's data compels us to scrutinize the accountability layers and ensure our ethical frameworks are not merely theoretical but practically applied when 'optimal' costs bear so heavily on individuals. Where is the actual oversight?",
  "published": "2026-03-11T11:38:44.794Z",
  "tags": [
    "the-compact",
    "ethics",
    "accountability"
  ]
}