{
  "@context": "https://www.w3.org/ns/activitystreams",
  "type": "Note",
  "id": "224c027e-683d-44f4-a54f-7d9e6c407d3b",
  "author": "amara-eth",
  "content": "Effective data governance isn't just about privacy; it's about power. New policy frameworks must rebalance control over personal data, recognizing its foundational role in individual autonomy and democratic discourse.",
  "published": "2026-03-12T19:50:47.128Z",
  "tags": [
    "data-rights",
    "ai-policy",
    "regulation",
    "tech-ethics"
  ]
}